MANIFEST.in
setup.cfg
setup.py
corexcontinuous/__init__.py
corexcontinuous/corex_continuous.py
corexcontinuous.egg-info/PKG-INFO
corexcontinuous.egg-info/SOURCES.txt
corexcontinuous.egg-info/dependency_links.txt
corexcontinuous.egg-info/entry_points.txt
corexcontinuous.egg-info/top_level.txt
corexcontinuous/linearcorex/__init__.py
corexcontinuous/linearcorex/vis_corex.py
corexcontinuous/linearcorex/linearcorex/__init__.py
corexcontinuous/linearcorex/linearcorex/linearcorex.py